{
  "title": "康奈尔大学",
  "subtitle": "2021 年 1 月至 2022 年 12 月在伊萨卡攻读 ECE M.Eng",
  "summary": "那是一段很快乐的时光，我在一个宁静、安静又有些偏远的大学城里认真生活。我尽量去探索纽约上州的风景，也真的很喜欢那里的秋天。我也抓住最后的机会去上所有自己感兴趣的课，其中有 6 门竟然还是体育课 :)",
  "tags": [
    "康奈尔",
    "研究生",
    "伊萨卡"
  ],
  "meta": {
    "dateLabel": "2021 年 8 月 - 2022 年 12 月",
    "location": "伊萨卡"
  },
  "sections": [
    {
      "label": "概览",
      "blocks": [
        {
          "type": "text",
          "text": "我本来应该在 2021 年入学，但后来的事情大家都知道。那场席卷全球的灾难永久地改变了我们的生活，我也不得不 gap 一年去处理各种琐事，不过最终还是在 2022 年 8 月到了伊萨卡。"
        },
        {
          "type": "text",
          "text": "我第一年住在北校区的一栋九卧室房子里，因为工学院在南边，几乎每天都要走十公里。最开始的几个月特别热闹，我们几乎每周都会有聚会，要么是给同学过生日，要么就是单纯找个理由开心一下。"
        },
        {
          "type": "text",
          "text": "后来，找暑期实习的煎熬和伊萨卡极寒的冬天一起到来了，我不得不花很多时间在面试准备和课程作业之间来回平衡。第一学期我并没有找到工作。"
        },
        {
          "type": "text",
          "text": "寒假短暂又严酷。有一天气温低到了零下 20 摄氏度，但我还是出门去拍了一张很好看的冰冻瀑布照片。"
        },
        {
          "type": "image",
          "alt": "冰封的伊萨卡瀑布",
          "src": "https://picx.zhimg.com/v2-e0773f6f1738c21c160b9b33ccf4e928_1440w.jpg?source=d16d100b",
          "caption": "第一次亲眼看到完全冻住的瀑布"
        },
        {
          "type": "text",
          "text": "冬天一直持续到第二年的四月，不过我很幸运，在三月、离生日还有两周的时候拿到了一个实习 offer。那时其实也没有太多选择，于是我签了下来，开始规划去加州过夏天。"
        },
        {
          "type": "text",
          "text": "后来我拿到了 return offer，所以最后一个学期过得相对轻松一些，也搬到了南校区。我上了品酒课，听了几场音乐会，也去冰场看比赛，还第一次在 Watertown 体验了白水漂流。"
        },
        {
          "type": "text",
          "text": "康奈尔在选课上其实很友好，给了学生相当大的自由度，所以我也趁这个机会选了六门体育课。第一学期是小帆船和壁球，第二学期是滑冰和射箭，最后一个学期则是拳击和桨板。"
        },
        {
          "type": "gallery",
          "items": [
            {
              "alt": "我站在冰场上",
              "src": "https://pic3.zhimg.com/v2-832b21e9f52b438871e1d0efe01f392c_1440w.jpg",
              "caption": "滑冰和滑雪、单板的感觉真的很不一样"
            },
            {
              "alt": "我们的毕业典礼",
              "src": "https://picx.zhimg.com/v2-f84dd59ed7ceca7195660cf451af7b10_1440w.jpg?source=d16d100b",
              "caption": "我们毕业啦！"
            }
          ],
          "columns": 2,
          "align": "height"
        },
        {
          "type": "text",
          "text": "我原本以为冬季毕业不会有毕业典礼。毕竟我们在 2020 年夏天就没有。但康奈尔在 12 月毕业的学生人数其实不少，所以最后还是办了一场相当像样的毕业典礼。"
        }
      ],
      "id": "overview"
    },
    {
      "label": "知乎文章",
      "blocks": [
        {
          "type": "text",
          "text": "一些关于这段经历的文章："
        },
        {
          "type": "list",
          "items": [
            "[康村基本情况—— Cornell ECE MENG 就读体验 - 1](https://zhuanlan.zhihu.com/p/673558343)",
            "[选课和课程体验 —— Cornell ECE MENG 就读体验 - 2](https://zhuanlan.zhihu.com/p/673560250)",
            "[找实习和找工作——Cornell ECE MENG 就读体验 - 3](https://zhuanlan.zhihu.com/p/673614414)"
          ]
        }
      ]
    }
  ],
  "detail": [
    {
      "type": "text",
      "text": "我本来应该在 2021 年入学，但后来的事情大家都知道。那场席卷全球的灾难永久地改变了我们的生活，我也不得不 gap 一年去处理各种琐事，不过最终还是在 2022 年 8 月到了伊萨卡。"
    },
    {
      "type": "text",
      "text": "我第一年住在北校区的一栋九卧室房子里，因为工学院在南边，几乎每天都要走十公里。最开始的几个月特别热闹，我们几乎每周都会有聚会，要么是给同学过生日，要么就是单纯找个理由开心一下。"
    },
    {
      "type": "text",
      "text": "一些关于这段经历的文章："
    }
  ]
}
