{
  "title": "RealAI 软件算法工程实习",
  "subtitle": "在北京的一段 AI 安全实习",
  "summary": "一段短暂的产业章节，围绕 AI 安全展开，位置正好落在学术鲁棒性研究与后来的产品工程工作之间。",
  "tags": [
    "工业界",
    "ai 安全"
  ],
  "sections": [
    {
      "id": "overview",
      "label": "概览",
      "blocks": [
        {
          "type": "text",
          "text": "RealAI 像一座桥。同样是对抗机器学习的兴趣，但被放到了更偏应用的环境里，由行业节奏与产品约束来塑形。它让人更明确地感受到：鲁棒性的想法必须在论文世界之外也站得住。"
        },
        {
          "type": "list",
          "items": [
            "担任软件算法工程师实习生",
            "持续靠近 AI 安全与鲁棒性主题",
            "帮助标记了从重研究工作走向工程岗位的转折"
          ]
        }
      ]
    }
  ]
}
