{
  "title": "California State Route 1",
  "subtitle": "A coastal drive during the Verily summer",
  "summary": "A Pacific coast travel node tied to the California internship period, with a scenic route through places like Half Moon Bay, Santa Cruz, Monterey, and 17-Mile Drive.",
  "tags": [
    "travel",
    "coast"
  ],
  "meta": {},
  "sections": [
    {
      "label": "Overview",
      "blocks": [
        {
          "type": "text",
          "text": "Start writing here."
        }
      ],
      "id": "overview"
    }
  ]
}
